nhentai_downloader/__init__.py
nhentai_downloader/main.py
nhentai_downloader/nhentai_downloader.py
nhentai_download-1.0.0.dist-info/LICENSE
nhentai_download-1.0.0.dist-info/METADATA
nhentai_download-1.0.0.dist-info/WHEEL
nhentai_download-1.0.0.dist-info/entry_points.txt
nhentai_download-1.0.0.dist-info/top_level.txt
nhentai_download-1.0.0.dist-info/RECORD
