Metadata-Version: 2.1
Name: nhentai-download
Version: 1.0.0
Summary: UNKNOWN
Home-page: https://github.com/TOKYOCOLD69/nhentai-downloader
Author: TOKYOCOLD69
Author-email: TOKYOCOLD69@gamil.com
License: MIT
Keywords: nhentai,downloader,anime
Platform: UNKNOWN
Requires-Python: >=3.6
License-File: LICENSE
Requires-Dist: beautifulsoup4 (>=4.9.3)
Requires-Dist: requests (>=2.22.0)
Requires-Dist: tqdm (>=4.62.0)
